ComunicationModule.v
// 8N1 UART Module, transmit only

module ComunicationModule (
    clk,        // input clock
    txbyte,     // outgoing byte
    senddata,   // trigger tx
    txdone,     // outgoing byte sent
    tx,         // tx wire
    );

    /* Inputs */
    input clk;
    input[7:0] txbyte;
    input senddata;

    /* Outputs */
    output txdone;
    output tx;

    /* Parameters */
    parameter STATE_IDLE=8'd0;
    parameter STATE_STARTTX=8'd1;
    parameter STATE_TXING=8'd2;
    parameter STATE_TXDONE=8'd3;

    /* State variables */
    reg[7:0] state=8'b0;
    reg[7:0] buf_tx=8'b0;
    reg[7:0] bits_sent=8'b0;
    reg txbit=1'b1;
    reg txdone=1'b0;

    /* Wiring */
    assign tx=txbit;

    /* always */
    always @ (posedge clk) begin
        // start sending?
        if (senddata == 1 && state == STATE_IDLE) begin
            state <= STATE_STARTTX;
            buf_tx <= txbyte;
            txdone <= 1'b0;
        end else if (state == STATE_IDLE) begin
            // idle at high
            txbit <= 1'b1;
            txdone <= 1'b0;
        end

        // send start bit (low)
        if (state == STATE_STARTTX) begin
            txbit <= 1'b0;
            state <= STATE_TXING;
        end
        // clock data out
        if (state == STATE_TXING && bits_sent < 8'd8) begin
            txbit <= buf_tx[0];
            buf_tx <= buf_tx>>1;
            bits_sent = bits_sent + 1;
        end else if (state == STATE_TXING) begin
            // send stop bit (high)
            txbit <= 1'b1;
            bits_sent <= 8'b0;
            state <= STATE_TXDONE;
        end

        // tx done
        if (state == STATE_TXDONE) begin
            txdone <= 1'b1;
            state <= STATE_IDLE;
        end

    end

endmodule

ComunicationModule_tb.v
`timescale 1us/1us

module ComunicationModule_tb;

    // Parameters
    parameter CLK_PERIOD = 100; // Clock period in ns

    // Signals
    reg clk;
    reg [7:0] txbyte;
    reg senddata;
    wire txdone;
    wire tx;

    // Instantiate the ComunicationModule
    ComunicationModule uut (
        .clk(clk),
        .txbyte(txbyte),
        .senddata(senddata),
        .txdone(txdone),
        .tx(tx)
    );

    // Clock generation
    initial begin
     clk = 0;
     forever #5 clk = ~clk;
    end

    // Initial block
    initial begin
        // Initialize inputs
        clk = 0;
        txbyte = 8'b11011010; // Example data
        senddata = 0;

        // Dump VCD file
        $dumpfile("ComunicationModule.vcd");
        $dumpvars(0, ComunicationModule_tb);

        // Apply stimulus
        #5 senddata = 1; // Trigger transmission

        // Monitor output
        $monitor("Time=%t, tx=%b, txdone=%b", $time, tx, txdone);

        // Run simulation for a while
        #100 $stop;
    end

endmodule

ComunicationModule.vcd
$date
	Wed Nov 29 17:27:30 2023
$end
$version
	Icarus Verilog
$end
$timescale
	1us
$end
$scope module ComunicationModule_tb $end
$var wire 1 ! tx $end
$var wire 1 " txdone $end
$var reg 1 # clk $end
$var reg 1 $ senddata $end
$var reg 8 % txbyte [7:0] $end
$scope module uut $end
$var wire 1 & clk $end
$var wire 1 ' senddata $end
$var wire 1 ! tx $end
$var wire 8 ( txbyte [7:0] $end
$var reg 8 ) bits_sent [7:0] $end
$var reg 8 * buf_tx [7:0] $end
$var reg 8 + state [7:0] $end
$var reg 1 , txbit $end
$var reg 1 - txdone $end
$upscope $end
$upscope $end
$enddefinitions $end
#0
$dumpvars
0-
1,
b0 +
b0 *
b0 )
b11011010 (
0'
0&
b11011010 %
0$
0#
0"
1!
$end
#5
b11011010 *
b1 +
1$
1'
1#
1&
#10
0#
0&
#15
b10 +
0,
0!
1#
1&
#20
0#
0&
#25
b1101101 *
b1 )
1#
1&
#30
0#
0&
#35
b110110 *
1,
1!
b10 )
1#
1&
#40
0#
0&
#45
b11011 *
0,
0!
b11 )
1#
1&
#50
0#
0&
#55
b1101 *
1,
1!
b100 )
1#
1&
#60
0#
0&
#65
b110 *
b101 )
1#
1&
#70
0#
0&
#75
b11 *
0,
0!
b110 )
1#
1&
#80
0#
0&
#85
b1 *
1,
1!
b111 )
1#
1&
#90
0#
0&
#95
b0 *
b1000 )
1#
1&
