DelayModule.v
module DelayModule (
  input wire clk,          // Señal de reloj
  input wire rst,          // Señal de reinicio
  input wire [8:0] delay,   // Valor de delay de 9 bits
  output reg out_delay     // Salida de delay
);

  reg [8:0] count;          // Contador de delay

  always @(posedge clk or posedge rst) begin
    if (rst) begin
      count <= 0;           // Reiniciar contador en caso de reinicio
      out_delay <= 0;       // Reiniciar salida en caso de reinicio
    end else begin
      if (count == delay) begin
        out_delay <= 1;     // Activar salida después del delay
        count <= 0;         // Reiniciar contador después del delay
      end else begin
        count <= count + 1; // Incrementar contador si no se alcanza el delay
        out_delay <= 0;     // Desactivar salida durante el delay
      end
    end
  end

endmodule

DelayModule_tb.v
`timescale 1us/1us

module DelayModule_tb;
  reg clk, rst;
  reg [8:0] delay;
  wire out_delay;

  // Instancia del módulo
  DelayModule uut (
    .clk(clk),
    .rst(rst),
    .delay(delay),
    .out_delay(out_delay)
  );

  // Generador de clock
  initial begin
    clk = 0;
    forever #5 clk = ~clk;
  end

  // Testbench
  initial begin
    // Inicialización de señales
    rst = 1;
    delay = 60;
    
    // Esperar un poco antes de desactivar el reset
    #10 rst = 0;

    // Simular durante 1000 unidades de tiempo
    #1000 $finish;
  end

  // Dumpfile y Dumpvars
  initial begin
    $dumpfile("DelayModule.vcd");
    $dumpvars(0, DelayModule_tb);
  end

endmodule

DelayModule.vcd
$date
	Sun Nov 19 18:57:01 2023
$end
$version
	Icarus Verilog
$end
$timescale
	1us
$end
$scope module DelayModule_tb $end
$var wire 1 ! out_delay $end
$var reg 1 " clk $end
$var reg 9 # delay [8:0] $end
$var reg 1 $ rst $end
$scope module uut $end
$var wire 1 % clk $end
$var wire 9 & delay [8:0] $end
$var wire 1 ' rst $end
$var reg 9 ( count [8:0] $end
$var reg 1 ) out_delay $end
$upscope $end
$upscope $end
$enddefinitions $end
#0
$dumpvars
0)
b0 (
1'
b111100 &
0%
1$
b111100 #
0"
0!
$end
#5
1"
1%
#10
0"
0%
0$
0'
#15
b1 (
1"
1%
#20
0"
0%
#25
b10 (
1"
1%
#30
0"
0%
#35
b11 (
1"
1%
#40
0"
0%
#45
b100 (
1"
1%
#50
0"
0%
#55
b101 (
1"
1%
#60
0"
0%
#65
b110 (
1"
1%
#70
0"
0%
#75
b111 (
1"
1%
#80
0"
0%
#85
b1000 (
1"
1%
#90
0"
0%
#95
b1001 (
1"
1%
#100
0"
0%
#105
b1010 (
1"
1%
#110
0"
0%
#115
b1011 (
1"
1%
#120
0"
0%
#125
b1100 (
1"
1%
#130
0"
0%
#135
b1101 (
1"
1%
#140
0"
0%
#145
b1110 (
1"
1%
#150
0"
0%
#155
b1111 (
1"
1%
#160
0"
0%
#165
b10000 (
1"
1%
#170
0"
0%
#175
b10001 (
1"
1%
#180
0"
0%
#185
b10010 (
1"
1%
#190
0"
0%
#195
b10011 (
1"
1%
#200
0"
0%
#205
b10100 (
1"
1%
#210
0"
0%
#215
b10101 (
1"
1%
#220
0"
0%
#225
b10110 (
1"
1%
#230
0"
0%
#235
b10111 (
1"
1%
#240
0"
0%
#245
b11000 (
1"
1%
#250
0"
0%
#255
b11001 (
1"
1%
#260
0"
0%
#265
b11010 (
1"
1%
#270
0"
0%
#275
b11011 (
1"
1%
#280
0"
0%
#285
b11100 (
1"
1%
#290
0"
0%
#295
b11101 (
1"
1%
#300
0"
0%
#305
b11110 (
1"
1%
#310
0"
0%
#315
b11111 (
1"
1%
#320
0"
0%
#325
b100000 (
1"
1%
#330
0"
0%
#335
b100001 (
1"
1%
#340
0"
0%
#345
b100010 (
1"
1%
#350
0"
0%
#355
b100011 (
1"
1%
#360
0"
0%
#365
b100100 (
1"
1%
#370
0"
0%
#375
b100101 (
1"
1%
#380
0"
0%
#385
b100110 (
1"
1%
#390
0"
0%
#395
b100111 (
1"
1%
#400
0"
0%
#405
b101000 (
1"
1%
#410
0"
0%
#415
b101001 (
1"
1%
#420
0"
0%
#425
b101010 (
1"
1%
#430
0"
0%
#435
b101011 (
1"
1%
#440
0"
0%
#445
b101100 (
1"
1%
#450
0"
0%
#455
b101101 (
1"
1%
#460
0"
0%
#465
b101110 (
1"
1%
#470
0"
0%
#475
b101111 (
1"
1%
#480
0"
0%
#485
b110000 (
1"
1%
#490
0"
0%
#495
b110001 (
1"
1%
#500
0"
0%
#505
b110010 (
1"
1%
#510
0"
0%
#515
b110011 (
1"
1%
#520
0"
0%
#525
b110100 (
1"
1%
#530
0"
0%
#535
b110101 (
1"
1%
#540
0"
0%
#545
b110110 (
1"
1%
#550
0"
0%
#555
b110111 (
1"
1%
#560
0"
0%
#565
b111000 (
1"
1%
#570
0"
0%
#575
b111001 (
1"
1%
#580
0"
0%
#585
b111010 (
1"
1%
#590
0"
0%
#595
b111011 (
1"
1%
#600
0"
0%
#605
b111100 (
1"
1%
#610
0"
0%
#615
b0 (
1)
1!
1"
1%
#620
0"
0%
#625
0)
0!
b1 (
1"
1%
#630
0"
0%
#635
b10 (
1"
1%
#640
0"
0%
#645
b11 (
1"
1%
#650
0"
0%
#655
b100 (
1"
1%
#660
0"
0%
#665
b101 (
1"
1%
#670
0"
0%
#675
b110 (
1"
1%
#680
0"
0%
#685
b111 (
1"
1%
#690
0"
0%
#695
b1000 (
1"
1%
#700
0"
0%
#705
b1001 (
1"
1%
#710
0"
0%
#715
b1010 (
1"
1%
#720
0"
0%
#725
b1011 (
1"
1%
#730
0"
0%
#735
b1100 (
1"
1%
#740
0"
0%
#745
b1101 (
1"
1%
#750
0"
0%
#755
b1110 (
1"
1%
#760
0"
0%
#765
b1111 (
1"
1%
#770
0"
0%
#775
b10000 (
1"
1%
#780
0"
0%
#785
b10001 (
1"
1%
#790
0"
0%
#795
b10010 (
1"
1%
#800
0"
0%
#805
b10011 (
1"
1%
#810
0"
0%
#815
b10100 (
1"
1%
#820
0"
0%
#825
b10101 (
1"
1%
#830
0"
0%
#835
b10110 (
1"
1%
#840
0"
0%
#845
b10111 (
1"
1%
#850
0"
0%
#855
b11000 (
1"
1%
#860
0"
0%
#865
b11001 (
1"
1%
#870
0"
0%
#875
b11010 (
1"
1%
#880
0"
0%
#885
b11011 (
1"
1%
#890
0"
0%
#895
b11100 (
1"
1%
#900
0"
0%
#905
b11101 (
1"
1%
#910
0"
0%
#915
b11110 (
1"
1%
#920
0"
0%
#925
b11111 (
1"
1%
#930
0"
0%
#935
b100000 (
1"
1%
#940
0"
0%
#945
b100001 (
1"
1%
#950
0"
0%
#955
b100010 (
1"
1%
#960
0"
0%
#965
b100011 (
1"
1%
#970
0"
0%
#975
b100100 (
1"
1%
#980
0"
0%
#985
b100101 (
1"
1%
#990
0"
0%
#995
b100110 (
1"
1%
#1000
0"
0%
#1005
b100111 (
1"
1%
