DelayModule.v
module DelayModule (
  input wire clk,          // Señal de reloj
  input wire rst,          // Señal de reinicio
  input wire [8:0] delay,   // Valor de delay de 9 bits
  output reg out_delay     // Salida de delay
);

  reg [8:0] count;          // Contador de delay

  always @(posedge clk or posedge rst) begin
    if (rst) begin
      count <= 0;           // Reiniciar contador en caso de reinicio
      out_delay <= 0;       // Reiniciar salida en caso de reinicio
    end else begin
      if (count == delay) begin
        out_delay <= 1;     // Activar salida después del delay
        count <= 0;         // Reiniciar contador después del delay
      end else begin
        count <= count + 1; // Incrementar contador si no se alcanza el delay
        out_delay <= 0;     // Desactivar salida durante el delay
      end
    end
  end

endmodule

ReadModule.v
module ReadModule (
  input wire clk,          // Señal de reloj
  input wire rst,          // Señal de reinicio
  input wire in_data,      // Entrada de datos
  output reg out_data      // Salida de datos
);

  reg [0:0] D1, D2, D;      // Variables para almacenar datos
  wire out_delay;          // Señal de salida del DelayModule
  reg [8:0] delay1 = 10;    // Delay de 10 ciclos para 1 microsegundo
  reg [8:0] delay2 = 600;   // Delay de 600 ciclos para 60 microsegundos

  // Instancia del DelayModule
  DelayModule delay_module (
    .clk(clk),
    .rst(rst),
    .delay(delay1),
    .out_delay(out_delay)
  );

  // Proceso principal
  always @(posedge clk or posedge rst) begin
    if (rst) begin
      // Reiniciar variables en caso de reinicio
      D1 <= 0;
      D2 <= 0;
      D <= 0;
      out_data <= 0;
    end else begin
      // Activar salida durante el primer delay
      if (out_delay) begin
        // Guardar el bit de entrada en D1
        D1 <= in_data;
      end

      // Activar salida durante el segundo delay
      if (out_delay) begin
        // Guardar el bit de entrada en D2
        D2 <= in_data;
      end

      // Comparar D1 y D2
      if (D1 == D2) begin
        // Si son iguales, guardar D1 en D
        D <= D1;
        out_data <= D;
      end else begin
        // Si son diferentes, imprimir "ERROR"
        $display("ERROR");
      end
    end
  end

endmodule

ComunicationModule.v
// 8N1 UART Module, transmit only

module ComunicationModule (
    clk,        // input clock
    txbyte,     // outgoing byte
    senddata,   // trigger tx
    txdone,     // outgoing byte sent
    tx,         // tx wire
    );

    /* Inputs */
    input clk;
    input[7:0] txbyte;
    input senddata;

    /* Outputs */
    output txdone;
    output tx;

    /* Parameters */
    parameter STATE_IDLE=8'd0;
    parameter STATE_STARTTX=8'd1;
    parameter STATE_TXING=8'd2;
    parameter STATE_TXDONE=8'd3;

    /* State variables */
    reg[7:0] state=8'b0;
    reg[7:0] buf_tx=8'b0;
    reg[7:0] bits_sent=8'b0;
    reg txbit=1'b1;
    reg txdone=1'b0;

    /* Wiring */
    assign tx=txbit;

    /* always */
    always @ (posedge clk) begin
        // start sending?
        if (senddata == 1 && state == STATE_IDLE) begin
            state <= STATE_STARTTX;
            buf_tx <= txbyte;
            txdone <= 1'b0;
        end else if (state == STATE_IDLE) begin
            // idle at high
            txbit <= 1'b1;
            txdone <= 1'b0;
        end

        // send start bit (low)
        if (state == STATE_STARTTX) begin
            txbit <= 1'b0;
            state <= STATE_TXING;
        end
        // clock data out
        if (state == STATE_TXING && bits_sent < 8'd8) begin
            txbit <= buf_tx[0];
            buf_tx <= buf_tx>>1;
            bits_sent = bits_sent + 1;
        end else if (state == STATE_TXING) begin
            // send stop bit (high)
            txbit <= 1'b1;
            bits_sent <= 8'b0;
            state <= STATE_TXDONE;
        end

        // tx done
        if (state == STATE_TXDONE) begin
            txdone <= 1'b1;
            state <= STATE_IDLE;
        end

    end

endmodule

DHT11.v
module DHT11(
    input wire clk,        // Entrada de reloj
    input wire rst,        // Entrada de reinicio
    input wire dht11_data, // Entrada de datos desde el sensor DHT11
    output ftdi_tx
);
wire dataReadModule;
reg [39:0] data;
reg clk_9600 = 0;
reg [31:0] cntr_9600 = 32'b0;
parameter period_9600 = 1302;
parameter ASCII_0 = 1'b1;
parameter ASCII_1 = 1'b0;
reg [7:0] uart_txbyte = ASCII_0;
reg uart_send = 1'b1;
wire uart_txed;
reg [3:0] state;           // Variable de estado
reg [7:0] bit_count;       // Variable de conteo de bits
reg [39:0] shift_register; // Registro de desplazamiento para almacenar 40 bits de datos
reg [0:0] D1, D2, D;      // Variables para almacenar datos
wire out_delay;          // Señal de salida del DelayModule
reg [8:0] delay1 = 10;    // Delay de 10 ciclos para 1 microsegundo
reg [8:0] delay2 = 600;   // Delay de 600 ciclos para 60 microsegundos
reg clk_1 = 0;
reg [31:0] cntr_1 = 32'b0;
parameter period_1 = 12500000;



  //Instancia del ComunicationModule
  ComunicationModule comunication_module(
    .clk(clk_9600),
    .txbyte (uart_txbyte),
    .senddata (uart_send),
    .txdone (uart_txed),
    .tx (ftdi_tx)
  );
  // Instancia del DelayModule
  DelayModule delay_module (
    .clk(clk),
    .rst(rst),
    .delay(delay1),
    .out_delay(out_delay)
  );

  // Instancia del ReadModule
  ReadModule read_module (
    .clk(clk),
    .rst(rst),
    .in_data(dht11_data),
    .out_data(dataReadModule)
  );

// Definir estados
parameter IDLE = 4'b0000;
parameter START = 4'b0001;
parameter READ = 4'b0010;
parameter DONE = 4'b0011;

always @ (posedge clk) begin
        /* generate 9600 Hz clock */
        cntr_9600 <= cntr_9600 + 1;
        if (cntr_9600 == period_9600) begin
            clk_9600 <= ~clk_9600;
            cntr_9600 <= 32'b0;
        end

        /* generate 1 Hz clock */
        cntr_1 <= cntr_1 + 1;
        if (cntr_1 == period_1) begin
            clk_1 <= ~clk_1;
            cntr_1 <= 32'b0;
        end
    end
  reg [7:0] count;
  reg toggle;

always @(posedge clk or posedge rst) begin
    if (rst) begin
        state <= IDLE;
        bit_count <= 8'b0;
        shift_register <= 40'b0;
    end else begin
        case (state)
            IDLE: begin
                    state <= START;
                    bit_count <= 8'b0;
                
            end
            START: begin
                state <= READ;
            end
            READ: begin
                if (bit_count < 8) begin
                    shift_register[bit_count] <= dht11_data;
		    uart_txbyte[bit_count] <= dht11_data;
                    bit_count <= bit_count + 1;
                end else begin
                    state <= DONE;
                end
            end
            DONE: begin
                // Procesar los 40 bits de datos 
                data <= shift_register;
                state <= IDLE;
            end
            default: state <= IDLE;
        endcase
    end
end

endmodule

DHT11_tb.v
module DHT11_tb;
  reg clk;
  reg rst;
  reg dht11_data;
  wire ftdi_tx;

  DHT11 uut (
    .clk(clk),
    .rst(rst),
    .dht11_data(dht11_data),
    .ftdi_tx(ftdi_tx)
  );

  initial begin
    $dumpfile("DHT11.vcd");
    $dumpvars(0, DHT11_tb);

    clk = 0;
    rst = 1;
    dht11_data = 1'b0;

    #10 rst = 0;  
    #50 rst = 1;
    #200 rst = 0;


    #20 dht11_data = 1'b1;  
    #30 dht11_data = 1'b0;
    #40 dht11_data = 1'b1;
    #100 dht11_data = 1'b0;  
    #500 dht11_data = 1'b1;
    #700 dht11_data = 1'b0;

    #1000 $finish;  
  end

  always begin
    #5 clk = ~clk;  
  end

endmodule

DHT11.vcd
$date
	Tue Dec 05 02:19:35 2023
$end
$version
	Icarus Verilog
$end
$timescale
	1s
$end
$scope module DHT11_tb $end
$var wire 1 ! ftdi_tx $end
$var reg 1 " clk $end
$var reg 1 # dht11_data $end
$var reg 1 $ rst $end
$scope module uut $end
$var wire 1 % clk $end
$var wire 1 & dataReadModule $end
$var wire 1 ' dht11_data $end
$var wire 1 ! ftdi_tx $end
$var wire 1 ( out_delay $end
$var wire 1 ) rst $end
$var wire 1 * uart_txed $end
$var reg 8 + bit_count [7:0] $end
$var reg 1 , clk_1 $end
$var reg 1 - clk_9600 $end
$var reg 32 . cntr_1 [31:0] $end
$var reg 32 / cntr_9600 [31:0] $end
$var reg 40 0 data [39:0] $end
$var reg 9 1 delay1 [8:0] $end
$var reg 9 2 delay2 [8:0] $end
$var reg 40 3 shift_register [39:0] $end
$var reg 4 4 state [3:0] $end
$var reg 1 5 uart_send $end
$var reg 8 6 uart_txbyte [7:0] $end
$scope module comunication_module $end
$var wire 1 7 clk $end
$var wire 1 8 senddata $end
$var wire 1 ! tx $end
$var wire 8 9 txbyte [7:0] $end
$var reg 8 : bits_sent [7:0] $end
$var reg 8 ; buf_tx [7:0] $end
$var reg 8 < state [7:0] $end
$var reg 1 = txbit $end
$var reg 1 > txdone $end
$upscope $end
$scope module delay_module $end
$var wire 1 % clk $end
$var wire 9 ? delay [8:0] $end
$var wire 1 ) rst $end
$var reg 9 @ count [8:0] $end
$var reg 1 A out_delay $end
$upscope $end
$scope module read_module $end
$var wire 1 % clk $end
$var wire 1 ' in_data $end
$var wire 1 B out_delay $end
$var wire 1 ) rst $end
$var reg 1 C D $end
$var reg 1 D D1 $end
$var reg 1 E D2 $end
$var reg 9 F delay1 [8:0] $end
$var reg 9 G delay2 [8:0] $end
$var reg 1 H out_data $end
$scope module delay_module $end
$var wire 1 % clk $end
$var wire 9 I delay [8:0] $end
$var wire 1 ) rst $end
$var reg 9 J count [8:0] $end
$var reg 1 K out_delay $end
$upscope $end
$upscope $end
$upscope $end
$upscope $end
$enddefinitions $end
#0
$dumpvars
0K
b0 J
b1010 I
0H
b1011000 G
b1010 F
0E
0D
0C
0B
0A
b0 @
b1010 ?
0>
1=
b0 <
b0 ;
b0 :
b1 9
18
07
b1 6
15
b0 4
b0 3
b1011000 2
b1010 1
bx 0
b0 /
b0 .
0-
0,
b0 +
0*
1)
0(
0'
0&
0%
1$
0#
0"
1!
$end
#5
b1 .
b1 /
1"
1%
#10
0"
0%
0$
0)
#15
b1 @
b1 J
b1 4
b10 .
b10 /
1"
1%
#20
0"
0%
#25
b10 4
b10 J
b10 @
b11 .
b11 /
1"
1%
#30
0"
0%
#35
b11 @
b11 J
b1 +
b0 6
b0 9
b0 3
b100 .
b100 /
1"
1%
#40
0"
0%
#45
b10 +
b0 6
b0 3
b100 J
b100 @
b101 .
b101 /
1"
1%
#50
0"
0%
#55
b101 @
b101 J
b11 +
b0 6
b0 3
b110 .
b110 /
1"
1%
#60
b0 +
b0 4
b0 J
b0 @
0"
0%
1$
1)
#65
b111 .
b111 /
1"
1%
#70
0"
0%
#75
b1000 .
b1000 /
1"
1%
#80
0"
0%
#85
b1001 .
b1001 /
1"
1%
#90
0"
0%
#95
b1010 .
b1010 /
1"
1%
#100
0"
0%
#105
b1011 .
b1011 /
1"
1%
#110
0"
0%
#115
b1100 .
b1100 /
1"
1%
#120
0"
0%
#125
b1101 .
b1101 /
1"
1%
#130
0"
0%
#135
b1110 .
b1110 /
1"
1%
#140
0"
0%
#145
b1111 .
b1111 /
1"
1%
#150
0"
0%
#155
b10000 .
b10000 /
1"
1%
#160
0"
0%
#165
b10001 .
b10001 /
1"
1%
#170
0"
0%
#175
b10010 .
b10010 /
1"
1%
#180
0"
0%
#185
b10011 .
b10011 /
1"
1%
#190
0"
0%
#195
b10100 .
b10100 /
1"
1%
#200
0"
0%
#205
b10101 .
b10101 /
1"
1%
#210
0"
0%
#215
b10110 .
b10110 /
1"
1%
#220
0"
0%
#225
b10111 .
b10111 /
1"
1%
#230
0"
0%
#235
b11000 .
b11000 /
1"
1%
#240
0"
0%
#245
b11001 .
b11001 /
1"
1%
#250
0"
0%
#255
b11010 .
b11010 /
1"
1%
#260
0"
0%
0$
0)
#265
b1 @
b1 J
b1 4
b11011 .
b11011 /
1"
1%
#270
0"
0%
#275
b10 4
b10 J
b10 @
b11100 .
b11100 /
1"
1%
#280
0"
0%
1#
1'
#285
b11 @
b11 J
b1 +
b1 6
b1 9
b1 3
b11101 .
b11101 /
1"
1%
#290
0"
0%
#295
b10 +
b11 6
b11 9
b11 3
b100 J
b100 @
b11110 .
b11110 /
1"
1%
#300
0"
0%
#305
b101 @
b101 J
b11 +
b111 6
b111 9
b111 3
b11111 .
b11111 /
1"
1%
#310
0"
0%
0#
0'
#315
b100 +
b111 6
b111 3
b110 J
b110 @
b100000 .
b100000 /
1"
1%
#320
0"
0%
#325
b111 @
b111 J
b101 +
b111 6
b111 3
b100001 .
b100001 /
1"
1%
#330
0"
0%
#335
b110 +
b111 6
b111 3
b1000 J
b1000 @
b100010 .
b100010 /
1"
1%
#340
0"
0%
#345
b1001 @
b1001 J
b111 +
b111 6
b111 3
b100011 .
b100011 /
1"
1%
#350
0"
0%
1#
1'
#355
b1000 +
b10000111 6
b10000111 9
b10000111 3
b1010 J
b1010 @
b100100 .
b100100 /
1"
1%
#360
0"
0%
#365
b0 @
1A
1(
b0 J
1K
1B
b11 4
b100101 .
b100101 /
1"
1%
#370
0"
0%
#375
b0 4
b10000111 0
1E
1D
0K
0B
b1 J
0A
0(
b1 @
b100110 .
b100110 /
1"
1%
#380
0"
0%
#385
b10 @
b10 J
1C
b0 +
b1 4
b100111 .
b100111 /
1"
1%
#390
0"
0%
#395
b10 4
1H
1&
b11 J
b11 @
b101000 .
b101000 /
1"
1%
#400
0"
0%
#405
b100 @
b100 J
b1 +
b10000111 6
b10000111 3
b101001 .
b101001 /
1"
1%
#410
0"
0%
#415
b10 +
b10000111 6
b10000111 3
b101 J
b101 @
b101010 .
b101010 /
1"
1%
#420
0"
0%
#425
b110 @
b110 J
b11 +
b10000111 6
b10000111 3
b101011 .
b101011 /
1"
1%
#430
0"
0%
#435
b100 +
b10001111 6
b10001111 9
b10001111 3
b111 J
b111 @
b101100 .
b101100 /
1"
1%
#440
0"
0%
#445
b1000 @
b1000 J
b101 +
b10011111 6
b10011111 9
b10011111 3
b101101 .
b101101 /
1"
1%
#450
0"
0%
0#
0'
#455
b110 +
b10011111 6
b10011111 3
b1001 J
b1001 @
b101110 .
b101110 /
1"
1%
#460
0"
0%
#465
b1010 @
b1010 J
b111 +
b10011111 6
b10011111 3
b101111 .
b101111 /
1"
1%
#470
0"
0%
#475
b1000 +
b11111 6
b11111 9
b11111 3
b0 J
1K
1B
b0 @
1A
1(
b110000 .
b110000 /
1"
1%
#480
0"
0%
#485
0A
0(
b1 @
0K
0B
b1 J
0E
0D
b11 4
b110001 .
b110001 /
1"
1%
#490
0"
0%
#495
b0 4
b11111 0
0C
b10 J
b10 @
b110010 .
b110010 /
1"
1%
#500
0"
0%
#505
b11 @
b11 J
0H
0&
b0 +
b1 4
b110011 .
b110011 /
1"
1%
#510
0"
0%
#515
b10 4
b100 J
b100 @
b110100 .
b110100 /
1"
1%
#520
0"
0%
#525
b101 @
b101 J
b1 +
b11110 6
b11110 9
b11110 3
b110101 .
b110101 /
1"
1%
#530
0"
0%
#535
b10 +
b11100 6
b11100 9
b11100 3
b110 J
b110 @
b110110 .
b110110 /
1"
1%
#540
0"
0%
#545
b111 @
b111 J
b11 +
b11000 6
b11000 9
b11000 3
b110111 .
b110111 /
1"
1%
#550
0"
0%
#555
b100 +
b10000 6
b10000 9
b10000 3
b1000 J
b1000 @
b111000 .
b111000 /
1"
1%
#560
0"
0%
#565
b1001 @
b1001 J
b101 +
b0 6
b0 9
b0 3
b111001 .
b111001 /
1"
1%
#570
0"
0%
#575
b110 +
b0 6
b0 3
b1010 J
b1010 @
b111010 .
b111010 /
1"
1%
#580
0"
0%
#585
b0 @
1A
1(
b0 J
1K
1B
b111 +
b0 6
b0 3
b111011 .
b111011 /
1"
1%
#590
0"
0%
#595
b1000 +
b0 6
b0 3
0K
0B
b1 J
0A
0(
b1 @
b111100 .
b111100 /
1"
1%
#600
0"
0%
#605
b10 @
b10 J
b11 4
b111101 .
b111101 /
1"
1%
#610
0"
0%
#615
b0 4
b0 0
b11 J
b11 @
b111110 .
b111110 /
1"
1%
#620
0"
0%
#625
b100 @
b100 J
b0 +
b1 4
b111111 .
b111111 /
1"
1%
#630
0"
0%
#635
b10 4
b101 J
b101 @
b1000000 .
b1000000 /
1"
1%
#640
0"
0%
#645
b110 @
b110 J
b1 +
b0 6
b0 3
b1000001 .
b1000001 /
1"
1%
#650
0"
0%
#655
b10 +
b0 6
b0 3
b111 J
b111 @
b1000010 .
b1000010 /
1"
1%
#660
0"
0%
#665
b1000 @
b1000 J
b11 +
b0 6
b0 3
b1000011 .
b1000011 /
1"
1%
#670
0"
0%
#675
b100 +
b0 6
b0 3
b1001 J
b1001 @
b1000100 .
b1000100 /
1"
1%
#680
0"
0%
#685
b1010 @
b1010 J
b101 +
b0 6
b0 3
b1000101 .
b1000101 /
1"
1%
#690
0"
0%
#695
b110 +
b0 6
b0 3
b0 J
1K
1B
b0 @
1A
1(
b1000110 .
b1000110 /
1"
1%
#700
0"
0%
#705
0A
0(
b1 @
0K
0B
b1 J
b111 +
b0 6
b0 3
b1000111 .
b1000111 /
1"
1%
#710
0"
0%
#715
b1000 +
b0 6
b0 3
b10 J
b10 @
b1001000 .
b1001000 /
1"
1%
#720
0"
0%
#725
b11 @
b11 J
b11 4
b1001001 .
b1001001 /
1"
1%
#730
0"
0%
#735
b0 4
b100 J
b100 @
b1001010 .
b1001010 /
1"
1%
#740
0"
0%
#745
b101 @
b101 J
b0 +
b1 4
b1001011 .
b1001011 /
1"
1%
#750
0"
0%
#755
b10 4
b110 J
b110 @
b1001100 .
b1001100 /
1"
1%
#760
0"
0%
#765
b111 @
b111 J
b1 +
b0 6
b0 3
b1001101 .
b1001101 /
1"
1%
#770
0"
0%
#775
b10 +
b0 6
b0 3
b1000 J
b1000 @
b1001110 .
b1001110 /
1"
1%
#780
0"
0%
#785
b1001 @
b1001 J
b11 +
b0 6
b0 3
b1001111 .
b1001111 /
1"
1%
#790
0"
0%
#795
b100 +
b0 6
b0 3
b1010 J
b1010 @
b1010000 .
b1010000 /
1"
1%
#800
0"
0%
#805
b0 @
1A
1(
b0 J
1K
1B
b101 +
b0 6
b0 3
b1010001 .
b1010001 /
1"
1%
#810
0"
0%
#815
b110 +
b0 6
b0 3
0K
0B
b1 J
0A
0(
b1 @
b1010010 .
b1010010 /
1"
1%
#820
0"
0%
#825
b10 @
b10 J
b111 +
b0 6
b0 3
b1010011 .
b1010011 /
1"
1%
#830
0"
0%
#835
b1000 +
b0 6
b0 3
b11 J
b11 @
b1010100 .
b1010100 /
1"
1%
#840
0"
0%
#845
b100 @
b100 J
b11 4
b1010101 .
b1010101 /
1"
1%
#850
0"
0%
#855
b0 4
b101 J
b101 @
b1010110 .
b1010110 /
1"
1%
#860
0"
0%
#865
b110 @
b110 J
b0 +
b1 4
b1010111 .
b1010111 /
1"
1%
#870
0"
0%
#875
b10 4
b111 J
b111 @
b1011000 .
b1011000 /
1"
1%
#880
0"
0%
#885
b1000 @
b1000 J
b1 +
b0 6
b0 3
b1011001 .
b1011001 /
1"
1%
#890
0"
0%
#895
b10 +
b0 6
b0 3
b1001 J
b1001 @
b1011010 .
b1011010 /
1"
1%
#900
0"
0%
#905
b1010 @
b1010 J
b11 +
b0 6
b0 3
b1011011 .
b1011011 /
1"
1%
#910
0"
0%
#915
b100 +
b0 6
b0 3
b0 J
1K
1B
b0 @
1A
1(
b1011100 .
b1011100 /
1"
1%
#920
0"
0%
#925
0A
0(
b1 @
0K
0B
b1 J
b101 +
b0 6
b0 3
b1011101 .
b1011101 /
1"
1%
#930
0"
0%
#935
b110 +
b0 6
b0 3
b10 J
b10 @
b1011110 .
b1011110 /
1"
1%
#940
0"
0%
#945
b11 @
b11 J
b111 +
b0 6
b0 3
b1011111 .
b1011111 /
1"
1%
#950
0"
0%
1#
1'
#955
b1000 +
b10000000 6
b10000000 9
b10000000 3
b100 J
b100 @
b1100000 .
b1100000 /
1"
1%
#960
0"
0%
#965
b101 @
b101 J
b11 4
b1100001 .
b1100001 /
1"
1%
#970
0"
0%
#975
b0 4
b10000000 0
b110 J
b110 @
b1100010 .
b1100010 /
1"
1%
#980
0"
0%
#985
b111 @
b111 J
b0 +
b1 4
b1100011 .
b1100011 /
1"
1%
#990
0"
0%
#995
b10 4
b1000 J
b1000 @
b1100100 .
b1100100 /
1"
1%
#1000
0"
0%
#1005
b1001 @
b1001 J
b1 +
b10000001 6
b10000001 9
b10000001 3
b1100101 .
b1100101 /
1"
1%
#1010
0"
0%
#1015
b10 +
b10000011 6
b10000011 9
b10000011 3
b1010 J
b1010 @
b1100110 .
b1100110 /
1"
1%
#1020
0"
0%
#1025
b0 @
1A
1(
b0 J
1K
1B
b11 +
b10000111 6
b10000111 9
b10000111 3
b1100111 .
b1100111 /
1"
1%
#1030
0"
0%
#1035
b100 +
b10001111 6
b10001111 9
b10001111 3
1E
1D
0K
0B
b1 J
0A
0(
b1 @
b1101000 .
b1101000 /
1"
1%
#1040
0"
0%
#1045
b10 @
b10 J
1C
b101 +
b10011111 6
b10011111 9
b10011111 3
b1101001 .
b1101001 /
1"
1%
#1050
0"
0%
#1055
b110 +
b10111111 6
b10111111 9
b10111111 3
1H
1&
b11 J
b11 @
b1101010 .
b1101010 /
1"
1%
#1060
0"
0%
#1065
b100 @
b100 J
b111 +
b11111111 6
b11111111 9
b11111111 3
b1101011 .
b1101011 /
1"
1%
#1070
0"
0%
#1075
b1000 +
b11111111 6
b11111111 3
b101 J
b101 @
b1101100 .
b1101100 /
1"
1%
#1080
0"
0%
#1085
b110 @
b110 J
b11 4
b1101101 .
b1101101 /
1"
1%
#1090
0"
0%
#1095
b0 4
b11111111 0
b111 J
b111 @
b1101110 .
b1101110 /
1"
1%
#1100
0"
0%
#1105
b1000 @
b1000 J
b0 +
b1 4
b1101111 .
b1101111 /
1"
1%
#1110
0"
0%
#1115
b10 4
b1001 J
b1001 @
b1110000 .
b1110000 /
1"
1%
#1120
0"
0%
#1125
b1010 @
b1010 J
b1 +
b11111111 6
b11111111 3
b1110001 .
b1110001 /
1"
1%
#1130
0"
0%
#1135
b10 +
b11111111 6
b11111111 3
b0 J
1K
1B
b0 @
1A
1(
b1110010 .
b1110010 /
1"
1%
#1140
0"
0%
#1145
0A
0(
b1 @
0K
0B
b1 J
b11 +
b11111111 6
b11111111 3
b1110011 .
b1110011 /
1"
1%
#1150
0"
0%
#1155
b100 +
b11111111 6
b11111111 3
b10 J
b10 @
b1110100 .
b1110100 /
1"
1%
#1160
0"
0%
#1165
b11 @
b11 J
b101 +
b11111111 6
b11111111 3
b1110101 .
b1110101 /
1"
1%
#1170
0"
0%
#1175
b110 +
b11111111 6
b11111111 3
b100 J
b100 @
b1110110 .
b1110110 /
1"
1%
#1180
0"
0%
#1185
b101 @
b101 J
b111 +
b11111111 6
b11111111 3
b1110111 .
b1110111 /
1"
1%
#1190
0"
0%
#1195
b1000 +
b11111111 6
b11111111 3
b110 J
b110 @
b1111000 .
b1111000 /
1"
1%
#1200
0"
0%
#1205
b111 @
b111 J
b11 4
b1111001 .
b1111001 /
1"
1%
#1210
0"
0%
#1215
b0 4
b1000 J
b1000 @
b1111010 .
b1111010 /
1"
1%
#1220
0"
0%
#1225
b1001 @
b1001 J
b0 +
b1 4
b1111011 .
b1111011 /
1"
1%
#1230
0"
0%
#1235
b10 4
b1010 J
b1010 @
b1111100 .
b1111100 /
1"
1%
#1240
0"
0%
#1245
b0 @
1A
1(
b0 J
1K
1B
b1 +
b11111111 6
b11111111 3
b1111101 .
b1111101 /
1"
1%
#1250
0"
0%
#1255
b10 +
b11111111 6
b11111111 3
0K
0B
b1 J
0A
0(
b1 @
b1111110 .
b1111110 /
1"
1%
#1260
0"
0%
#1265
b10 @
b10 J
b11 +
b11111111 6
b11111111 3
b1111111 .
b1111111 /
1"
1%
#1270
0"
0%
#1275
b100 +
b11111111 6
b11111111 3
b11 J
b11 @
b10000000 .
b10000000 /
1"
1%
#1280
0"
0%
#1285
b100 @
b100 J
b101 +
b11111111 6
b11111111 3
b10000001 .
b10000001 /
1"
1%
#1290
0"
0%
#1295
b110 +
b11111111 6
b11111111 3
b101 J
b101 @
b10000010 .
b10000010 /
1"
1%
#1300
0"
0%
#1305
b110 @
b110 J
b111 +
b11111111 6
b11111111 3
b10000011 .
b10000011 /
1"
1%
#1310
0"
0%
#1315
b1000 +
b11111111 6
b11111111 3
b111 J
b111 @
b10000100 .
b10000100 /
1"
1%
#1320
0"
0%
#1325
b1000 @
b1000 J
b11 4
b10000101 .
b10000101 /
1"
1%
#1330
0"
0%
#1335
b0 4
b1001 J
b1001 @
b10000110 .
b10000110 /
1"
1%
#1340
0"
0%
#1345
b1010 @
b1010 J
b0 +
b1 4
b10000111 .
b10000111 /
1"
1%
#1350
0"
0%
#1355
b10 4
b0 J
1K
1B
b0 @
1A
1(
b10001000 .
b10001000 /
1"
1%
#1360
0"
0%
#1365
0A
0(
b1 @
0K
0B
b1 J
b1 +
b11111111 6
b11111111 3
b10001001 .
b10001001 /
1"
1%
#1370
0"
0%
#1375
b10 +
b11111111 6
b11111111 3
b10 J
b10 @
b10001010 .
b10001010 /
1"
1%
#1380
0"
0%
#1385
b11 @
b11 J
b11 +
b11111111 6
b11111111 3
b10001011 .
b10001011 /
1"
1%
#1390
0"
0%
#1395
b100 +
b11111111 6
b11111111 3
b100 J
b100 @
b10001100 .
b10001100 /
1"
1%
#1400
0"
0%
#1405
b101 @
b101 J
b101 +
b11111111 6
b11111111 3
b10001101 .
b10001101 /
1"
1%
#1410
0"
0%
#1415
b110 +
b11111111 6
b11111111 3
b110 J
b110 @
b10001110 .
b10001110 /
1"
1%
#1420
0"
0%
#1425
b111 @
b111 J
b111 +
b11111111 6
b11111111 3
b10001111 .
b10001111 /
1"
1%
#1430
0"
0%
#1435
b1000 +
b11111111 6
b11111111 3
b1000 J
b1000 @
b10010000 .
b10010000 /
1"
1%
#1440
0"
0%
#1445
b1001 @
b1001 J
b11 4
b10010001 .
b10010001 /
1"
1%
#1450
0"
0%
#1455
b0 4
b1010 J
b1010 @
b10010010 .
b10010010 /
1"
1%
#1460
0"
0%
#1465
b0 @
1A
1(
b0 J
1K
1B
b0 +
b1 4
b10010011 .
b10010011 /
1"
1%
#1470
0"
0%
#1475
b10 4
0K
0B
b1 J
0A
0(
b1 @
b10010100 .
b10010100 /
1"
1%
#1480
0"
0%
#1485
b10 @
b10 J
b1 +
b11111111 6
b11111111 3
b10010101 .
b10010101 /
1"
1%
#1490
0"
0%
#1495
b10 +
b11111111 6
b11111111 3
b11 J
b11 @
b10010110 .
b10010110 /
1"
1%
#1500
0"
0%
#1505
b100 @
b100 J
b11 +
b11111111 6
b11111111 3
b10010111 .
b10010111 /
1"
1%
#1510
0"
0%
#1515
b100 +
b11111111 6
b11111111 3
b101 J
b101 @
b10011000 .
b10011000 /
1"
1%
#1520
0"
0%
#1525
b110 @
b110 J
b101 +
b11111111 6
b11111111 3
b10011001 .
b10011001 /
1"
1%
#1530
0"
0%
#1535
b110 +
b11111111 6
b11111111 3
b111 J
b111 @
b10011010 .
b10011010 /
1"
1%
#1540
0"
0%
#1545
b1000 @
b1000 J
b111 +
b11111111 6
b11111111 3
b10011011 .
b10011011 /
1"
1%
#1550
0"
0%
#1555
b1000 +
b11111111 6
b11111111 3
b1001 J
b1001 @
b10011100 .
b10011100 /
1"
1%
#1560
0"
0%
#1565
b1010 @
b1010 J
b11 4
b10011101 .
b10011101 /
1"
1%
#1570
0"
0%
#1575
b0 4
b0 J
1K
1B
b0 @
1A
1(
b10011110 .
b10011110 /
1"
1%
#1580
0"
0%
#1585
0A
0(
b1 @
0K
0B
b1 J
b0 +
b1 4
b10011111 .
b10011111 /
1"
1%
#1590
0"
0%
#1595
b10 4
b10 J
b10 @
b10100000 .
b10100000 /
1"
1%
#1600
0"
0%
#1605
b11 @
b11 J
b1 +
b11111111 6
b11111111 3
b10100001 .
b10100001 /
1"
1%
#1610
0"
0%
#1615
b10 +
b11111111 6
b11111111 3
b100 J
b100 @
b10100010 .
b10100010 /
1"
1%
#1620
0"
0%
#1625
b101 @
b101 J
b11 +
b11111111 6
b11111111 3
b10100011 .
b10100011 /
1"
1%
#1630
0"
0%
#1635
b100 +
b11111111 6
b11111111 3
b110 J
b110 @
b10100100 .
b10100100 /
1"
1%
#1640
0"
0%
#1645
b111 @
b111 J
b101 +
b11111111 6
b11111111 3
b10100101 .
b10100101 /
1"
1%
#1650
0"
0%
0#
0'
#1655
b110 +
b11011111 6
b11011111 9
b11011111 3
b1000 J
b1000 @
b10100110 .
b10100110 /
1"
1%
#1660
0"
0%
#1665
b1001 @
b1001 J
b111 +
b10011111 6
b10011111 9
b10011111 3
b10100111 .
b10100111 /
1"
1%
#1670
0"
0%
#1675
b1000 +
b11111 6
b11111 9
b11111 3
b1010 J
b1010 @
b10101000 .
b10101000 /
1"
1%
#1680
0"
0%
#1685
b0 @
1A
1(
b0 J
1K
1B
b11 4
b10101001 .
b10101001 /
1"
1%
#1690
0"
0%
#1695
b0 4
b11111 0
0E
0D
0K
0B
b1 J
0A
0(
b1 @
b10101010 .
b10101010 /
1"
1%
#1700
0"
0%
#1705
b10 @
b10 J
0C
b0 +
b1 4
b10101011 .
b10101011 /
1"
1%
#1710
0"
0%
#1715
b10 4
0H
0&
b11 J
b11 @
b10101100 .
b10101100 /
1"
1%
#1720
0"
0%
#1725
b100 @
b100 J
b1 +
b11110 6
b11110 9
b11110 3
b10101101 .
b10101101 /
1"
1%
#1730
0"
0%
#1735
b10 +
b11100 6
b11100 9
b11100 3
b101 J
b101 @
b10101110 .
b10101110 /
1"
1%
#1740
0"
0%
#1745
b110 @
b110 J
b11 +
b11000 6
b11000 9
b11000 3
b10101111 .
b10101111 /
1"
1%
#1750
0"
0%
#1755
b100 +
b10000 6
b10000 9
b10000 3
b111 J
b111 @
b10110000 .
b10110000 /
1"
1%
#1760
0"
0%
#1765
b1000 @
b1000 J
b101 +
b0 6
b0 9
b0 3
b10110001 .
b10110001 /
1"
1%
#1770
0"
0%
#1775
b110 +
b0 6
b0 3
b1001 J
b1001 @
b10110010 .
b10110010 /
1"
1%
#1780
0"
0%
#1785
b1010 @
b1010 J
b111 +
b0 6
b0 3
b10110011 .
b10110011 /
1"
1%
#1790
0"
0%
#1795
b1000 +
b0 6
b0 3
b0 J
1K
1B
b0 @
1A
1(
b10110100 .
b10110100 /
1"
1%
#1800
0"
0%
