DivisorFrecuencia.v
module DivisorFrecuencia (
  input wire clk,
  input wire reset,
  output wire out
);

  reg [7:0] count;
  reg toggle;

  always @(posedge clk or posedge reset) begin
    if (reset) begin
      count <= 8'b0;
      toggle <= 1'b0;
    end else begin
      if (count == 8'd124) begin  // Contador para 125 (125 = 2^3 * 5^3) para lograr la división de frecuencia
        count <= 8'b0;
        toggle <= ~toggle;
      end else begin
        count <= count + 1;
      end
    end
  end

  assign out = toggle;

endmodule

DivisorFrecuencia_tb.v
module DivisorFrecuencia_tb;

  reg clk;
  reg reset;
  wire out;

  DivisorFrecuencia uut (
    .clk(clk),
    .reset(reset),
    .out(out)
  );

  initial begin
    clk = 0;
    reset = 0;

    // Inicialización de la simulación
    $dumpfile("DivisorFrecuencia.vcd");
    $dumpvars(0, DivisorFrecuencia_tb);

    // Generación de pulsos de reloj
    repeat (200) begin
      #5 clk = ~clk;
    end

    // Aplicación de reset
    reset = 1;
    #10 reset = 0;

    // Ejecución de la simulación
    repeat (400) begin
      #5 clk = ~clk;
    end

    // Fin de la simulación
    $finish;
  end

endmodule

DivisorFrecuencia.vcd
$date
	Sun Nov 19 17:23:28 2023
$end
$version
	Icarus Verilog
$end
$timescale
	1s
$end
$scope module DivisorFrecuencia_tb $end
$var wire 1 ! out $end
$var reg 1 " clk $end
$var reg 1 # reset $end
$scope module uut $end
$var wire 1 $ clk $end
$var wire 1 ! out $end
$var wire 1 % reset $end
$var reg 8 & count [7:0] $end
$var reg 1 ' toggle $end
$upscope $end
$upscope $end
$enddefinitions $end
#0
$dumpvars
x'
bx &
0%
0$
0#
0"
x!
$end
#5
1"
1$
#10
0"
0$
#15
1"
1$
#20
0"
0$
#25
1"
1$
#30
0"
0$
#35
1"
1$
#40
0"
0$
#45
1"
1$
#50
0"
0$
#55
1"
1$
#60
0"
0$
#65
1"
1$
#70
0"
0$
#75
1"
1$
#80
0"
0$
#85
1"
1$
#90
0"
0$
#95
1"
1$
#100
0"
0$
#105
1"
1$
#110
0"
0$
#115
1"
1$
#120
0"
0$
#125
1"
1$
#130
0"
0$
#135
1"
1$
#140
0"
0$
#145
1"
1$
#150
0"
0$
#155
1"
1$
#160
0"
0$
#165
1"
1$
#170
0"
0$
#175
1"
1$
#180
0"
0$
#185
1"
1$
#190
0"
0$
#195
1"
1$
#200
0"
0$
#205
1"
1$
#210
0"
0$
#215
1"
1$
#220
0"
0$
#225
1"
1$
#230
0"
0$
#235
1"
1$
#240
0"
0$
#245
1"
1$
#250
0"
0$
#255
1"
1$
#260
0"
0$
#265
1"
1$
#270
0"
0$
#275
1"
1$
#280
0"
0$
#285
1"
1$
#290
0"
0$
#295
1"
1$
#300
0"
0$
#305
1"
1$
#310
0"
0$
#315
1"
1$
#320
0"
0$
#325
1"
1$
#330
0"
0$
#335
1"
1$
#340
0"
0$
#345
1"
1$
#350
0"
0$
#355
1"
1$
#360
0"
0$
#365
1"
1$
#370
0"
0$
#375
1"
1$
#380
0"
0$
#385
1"
1$
#390
0"
0$
#395
1"
1$
#400
0"
0$
#405
1"
1$
#410
0"
0$
#415
1"
1$
#420
0"
0$
#425
1"
1$
#430
0"
0$
#435
1"
1$
#440
0"
0$
#445
1"
1$
#450
0"
0$
#455
1"
1$
#460
0"
0$
#465
1"
1$
#470
0"
0$
#475
1"
1$
#480
0"
0$
#485
1"
1$
#490
0"
0$
#495
1"
1$
#500
0"
0$
#505
1"
1$
#510
0"
0$
#515
1"
1$
#520
0"
0$
#525
1"
1$
#530
0"
0$
#535
1"
1$
#540
0"
0$
#545
1"
1$
#550
0"
0$
#555
1"
1$
#560
0"
0$
#565
1"
1$
#570
0"
0$
#575
1"
1$
#580
0"
0$
#585
1"
1$
#590
0"
0$
#595
1"
1$
#600
0"
0$
#605
1"
1$
#610
0"
0$
#615
1"
1$
#620
0"
0$
#625
1"
1$
#630
0"
0$
#635
1"
1$
#640
0"
0$
#645
1"
1$
#650
0"
0$
#655
1"
1$
#660
0"
0$
#665
1"
1$
#670
0"
0$
#675
1"
1$
#680
0"
0$
#685
1"
1$
#690
0"
0$
#695
1"
1$
#700
0"
0$
#705
1"
1$
#710
0"
0$
#715
1"
1$
#720
0"
0$
#725
1"
1$
#730
0"
0$
#735
1"
1$
#740
0"
0$
#745
1"
1$
#750
0"
0$
#755
1"
1$
#760
0"
0$
#765
1"
1$
#770
0"
0$
#775
1"
1$
#780
0"
0$
#785
1"
1$
#790
0"
0$
#795
1"
1$
#800
0"
0$
#805
1"
1$
#810
0"
0$
#815
1"
1$
#820
0"
0$
#825
1"
1$
#830
0"
0$
#835
1"
1$
#840
0"
0$
#845
1"
1$
#850
0"
0$
#855
1"
1$
#860
0"
0$
#865
1"
1$
#870
0"
0$
#875
1"
1$
#880
0"
0$
#885
1"
1$
#890
0"
0$
#895
1"
1$
#900
0"
0$
#905
1"
1$
#910
0"
0$
#915
1"
1$
#920
0"
0$
#925
1"
1$
#930
0"
0$
#935
1"
1$
#940
0"
0$
#945
1"
1$
#950
0"
0$
#955
1"
1$
#960
0"
0$
#965
1"
1$
#970
0"
0$
#975
1"
1$
#980
0"
0$
#985
1"
1$
#990
0"
0$
#995
1"
1$
#1000
0'
0!
b0 &
1#
1%
0"
0$
#1010
0#
0%
#1015
b1 &
1"
1$
#1020
0"
0$
#1025
b10 &
1"
1$
#1030
0"
0$
#1035
b11 &
1"
1$
#1040
0"
0$
#1045
b100 &
1"
1$
#1050
0"
0$
#1055
b101 &
1"
1$
#1060
0"
0$
#1065
b110 &
1"
1$
#1070
0"
0$
#1075
b111 &
1"
1$
#1080
0"
0$
#1085
b1000 &
1"
1$
#1090
0"
0$
#1095
b1001 &
1"
1$
#1100
0"
0$
#1105
b1010 &
1"
1$
#1110
0"
0$
#1115
b1011 &
1"
1$
#1120
0"
0$
#1125
b1100 &
1"
1$
#1130
0"
0$
#1135
b1101 &
1"
1$
#1140
0"
0$
#1145
b1110 &
1"
1$
#1150
0"
0$
#1155
b1111 &
1"
1$
#1160
0"
0$
#1165
b10000 &
1"
1$
#1170
0"
0$
#1175
b10001 &
1"
1$
#1180
0"
0$
#1185
b10010 &
1"
1$
#1190
0"
0$
#1195
b10011 &
1"
1$
#1200
0"
0$
#1205
b10100 &
1"
1$
#1210
0"
0$
#1215
b10101 &
1"
1$
#1220
0"
0$
#1225
b10110 &
1"
1$
#1230
0"
0$
#1235
b10111 &
1"
1$
#1240
0"
0$
#1245
b11000 &
1"
1$
#1250
0"
0$
#1255
b11001 &
1"
1$
#1260
0"
0$
#1265
b11010 &
1"
1$
#1270
0"
0$
#1275
b11011 &
1"
1$
#1280
0"
0$
#1285
b11100 &
1"
1$
#1290
0"
0$
#1295
b11101 &
1"
1$
#1300
0"
0$
#1305
b11110 &
1"
1$
#1310
0"
0$
#1315
b11111 &
1"
1$
#1320
0"
0$
#1325
b100000 &
1"
1$
#1330
0"
0$
#1335
b100001 &
1"
1$
#1340
0"
0$
#1345
b100010 &
1"
1$
#1350
0"
0$
#1355
b100011 &
1"
1$
#1360
0"
0$
#1365
b100100 &
1"
1$
#1370
0"
0$
#1375
b100101 &
1"
1$
#1380
0"
0$
#1385
b100110 &
1"
1$
#1390
0"
0$
#1395
b100111 &
1"
1$
#1400
0"
0$
#1405
b101000 &
1"
1$
#1410
0"
0$
#1415
b101001 &
1"
1$
#1420
0"
0$
#1425
b101010 &
1"
1$
#1430
0"
0$
#1435
b101011 &
1"
1$
#1440
0"
0$
#1445
b101100 &
1"
1$
#1450
0"
0$
#1455
b101101 &
1"
1$
#1460
0"
0$
#1465
b101110 &
1"
1$
#1470
0"
0$
#1475
b101111 &
1"
1$
#1480
0"
0$
#1485
b110000 &
1"
1$
#1490
0"
0$
#1495
b110001 &
1"
1$
#1500
0"
0$
#1505
b110010 &
1"
1$
#1510
0"
0$
#1515
b110011 &
1"
1$
#1520
0"
0$
#1525
b110100 &
1"
1$
#1530
0"
0$
#1535
b110101 &
1"
1$
#1540
0"
0$
#1545
b110110 &
1"
1$
#1550
0"
0$
#1555
b110111 &
1"
1$
#1560
0"
0$
#1565
b111000 &
1"
1$
#1570
0"
0$
#1575
b111001 &
1"
1$
#1580
0"
0$
#1585
b111010 &
1"
1$
#1590
0"
0$
#1595
b111011 &
1"
1$
#1600
0"
0$
#1605
b111100 &
1"
1$
#1610
0"
0$
#1615
b111101 &
1"
1$
#1620
0"
0$
#1625
b111110 &
1"
1$
#1630
0"
0$
#1635
b111111 &
1"
1$
#1640
0"
0$
#1645
b1000000 &
1"
1$
#1650
0"
0$
#1655
b1000001 &
1"
1$
#1660
0"
0$
#1665
b1000010 &
1"
1$
#1670
0"
0$
#1675
b1000011 &
1"
1$
#1680
0"
0$
#1685
b1000100 &
1"
1$
#1690
0"
0$
#1695
b1000101 &
1"
1$
#1700
0"
0$
#1705
b1000110 &
1"
1$
#1710
0"
0$
#1715
b1000111 &
1"
1$
#1720
0"
0$
#1725
b1001000 &
1"
1$
#1730
0"
0$
#1735
b1001001 &
1"
1$
#1740
0"
0$
#1745
b1001010 &
1"
1$
#1750
0"
0$
#1755
b1001011 &
1"
1$
#1760
0"
0$
#1765
b1001100 &
1"
1$
#1770
0"
0$
#1775
b1001101 &
1"
1$
#1780
0"
0$
#1785
b1001110 &
1"
1$
#1790
0"
0$
#1795
b1001111 &
1"
1$
#1800
0"
0$
#1805
b1010000 &
1"
1$
#1810
0"
0$
#1815
b1010001 &
1"
1$
#1820
0"
0$
#1825
b1010010 &
1"
1$
#1830
0"
0$
#1835
b1010011 &
1"
1$
#1840
0"
0$
#1845
b1010100 &
1"
1$
#1850
0"
0$
#1855
b1010101 &
1"
1$
#1860
0"
0$
#1865
b1010110 &
1"
1$
#1870
0"
0$
#1875
b1010111 &
1"
1$
#1880
0"
0$
#1885
b1011000 &
1"
1$
#1890
0"
0$
#1895
b1011001 &
1"
1$
#1900
0"
0$
#1905
b1011010 &
1"
1$
#1910
0"
0$
#1915
b1011011 &
1"
1$
#1920
0"
0$
#1925
b1011100 &
1"
1$
#1930
0"
0$
#1935
b1011101 &
1"
1$
#1940
0"
0$
#1945
b1011110 &
1"
1$
#1950
0"
0$
#1955
b1011111 &
1"
1$
#1960
0"
0$
#1965
b1100000 &
1"
1$
#1970
0"
0$
#1975
b1100001 &
1"
1$
#1980
0"
0$
#1985
b1100010 &
1"
1$
#1990
0"
0$
#1995
b1100011 &
1"
1$
#2000
0"
0$
#2005
b1100100 &
1"
1$
#2010
0"
0$
#2015
b1100101 &
1"
1$
#2020
0"
0$
#2025
b1100110 &
1"
1$
#2030
0"
0$
#2035
b1100111 &
1"
1$
#2040
0"
0$
#2045
b1101000 &
1"
1$
#2050
0"
0$
#2055
b1101001 &
1"
1$
#2060
0"
0$
#2065
b1101010 &
1"
1$
#2070
0"
0$
#2075
b1101011 &
1"
1$
#2080
0"
0$
#2085
b1101100 &
1"
1$
#2090
0"
0$
#2095
b1101101 &
1"
1$
#2100
0"
0$
#2105
b1101110 &
1"
1$
#2110
0"
0$
#2115
b1101111 &
1"
1$
#2120
0"
0$
#2125
b1110000 &
1"
1$
#2130
0"
0$
#2135
b1110001 &
1"
1$
#2140
0"
0$
#2145
b1110010 &
1"
1$
#2150
0"
0$
#2155
b1110011 &
1"
1$
#2160
0"
0$
#2165
b1110100 &
1"
1$
#2170
0"
0$
#2175
b1110101 &
1"
1$
#2180
0"
0$
#2185
b1110110 &
1"
1$
#2190
0"
0$
#2195
b1110111 &
1"
1$
#2200
0"
0$
#2205
b1111000 &
1"
1$
#2210
0"
0$
#2215
b1111001 &
1"
1$
#2220
0"
0$
#2225
b1111010 &
1"
1$
#2230
0"
0$
#2235
b1111011 &
1"
1$
#2240
0"
0$
#2245
b1111100 &
1"
1$
#2250
0"
0$
#2255
1'
1!
b0 &
1"
1$
#2260
0"
0$
#2265
b1 &
1"
1$
#2270
0"
0$
#2275
b10 &
1"
1$
#2280
0"
0$
#2285
b11 &
1"
1$
#2290
0"
0$
#2295
b100 &
1"
1$
#2300
0"
0$
#2305
b101 &
1"
1$
#2310
0"
0$
#2315
b110 &
1"
1$
#2320
0"
0$
#2325
b111 &
1"
1$
#2330
0"
0$
#2335
b1000 &
1"
1$
#2340
0"
0$
#2345
b1001 &
1"
1$
#2350
0"
0$
#2355
b1010 &
1"
1$
#2360
0"
0$
#2365
b1011 &
1"
1$
#2370
0"
0$
#2375
b1100 &
1"
1$
#2380
0"
0$
#2385
b1101 &
1"
1$
#2390
0"
0$
#2395
b1110 &
1"
1$
#2400
0"
0$
#2405
b1111 &
1"
1$
#2410
0"
0$
#2415
b10000 &
1"
1$
#2420
0"
0$
#2425
b10001 &
1"
1$
#2430
0"
0$
#2435
b10010 &
1"
1$
#2440
0"
0$
#2445
b10011 &
1"
1$
#2450
0"
0$
#2455
b10100 &
1"
1$
#2460
0"
0$
#2465
b10101 &
1"
1$
#2470
0"
0$
#2475
b10110 &
1"
1$
#2480
0"
0$
#2485
b10111 &
1"
1$
#2490
0"
0$
#2495
b11000 &
1"
1$
#2500
0"
0$
#2505
b11001 &
1"
1$
#2510
0"
0$
#2515
b11010 &
1"
1$
#2520
0"
0$
#2525
b11011 &
1"
1$
#2530
0"
0$
#2535
b11100 &
1"
1$
#2540
0"
0$
#2545
b11101 &
1"
1$
#2550
0"
0$
#2555
b11110 &
1"
1$
#2560
0"
0$
#2565
b11111 &
1"
1$
#2570
0"
0$
#2575
b100000 &
1"
1$
#2580
0"
0$
#2585
b100001 &
1"
1$
#2590
0"
0$
#2595
b100010 &
1"
1$
#2600
0"
0$
#2605
b100011 &
1"
1$
#2610
0"
0$
#2615
b100100 &
1"
1$
#2620
0"
0$
#2625
b100101 &
1"
1$
#2630
0"
0$
#2635
b100110 &
1"
1$
#2640
0"
0$
#2645
b100111 &
1"
1$
#2650
0"
0$
#2655
b101000 &
1"
1$
#2660
0"
0$
#2665
b101001 &
1"
1$
#2670
0"
0$
#2675
b101010 &
1"
1$
#2680
0"
0$
#2685
b101011 &
1"
1$
#2690
0"
0$
#2695
b101100 &
1"
1$
#2700
0"
0$
#2705
b101101 &
1"
1$
#2710
0"
0$
#2715
b101110 &
1"
1$
#2720
0"
0$
#2725
b101111 &
1"
1$
#2730
0"
0$
#2735
b110000 &
1"
1$
#2740
0"
0$
#2745
b110001 &
1"
1$
#2750
0"
0$
#2755
b110010 &
1"
1$
#2760
0"
0$
#2765
b110011 &
1"
1$
#2770
0"
0$
#2775
b110100 &
1"
1$
#2780
0"
0$
#2785
b110101 &
1"
1$
#2790
0"
0$
#2795
b110110 &
1"
1$
#2800
0"
0$
#2805
b110111 &
1"
1$
#2810
0"
0$
#2815
b111000 &
1"
1$
#2820
0"
0$
#2825
b111001 &
1"
1$
#2830
0"
0$
#2835
b111010 &
1"
1$
#2840
0"
0$
#2845
b111011 &
1"
1$
#2850
0"
0$
#2855
b111100 &
1"
1$
#2860
0"
0$
#2865
b111101 &
1"
1$
#2870
0"
0$
#2875
b111110 &
1"
1$
#2880
0"
0$
#2885
b111111 &
1"
1$
#2890
0"
0$
#2895
b1000000 &
1"
1$
#2900
0"
0$
#2905
b1000001 &
1"
1$
#2910
0"
0$
#2915
b1000010 &
1"
1$
#2920
0"
0$
#2925
b1000011 &
1"
1$
#2930
0"
0$
#2935
b1000100 &
1"
1$
#2940
0"
0$
#2945
b1000101 &
1"
1$
#2950
0"
0$
#2955
b1000110 &
1"
1$
#2960
0"
0$
#2965
b1000111 &
1"
1$
#2970
0"
0$
#2975
b1001000 &
1"
1$
#2980
0"
0$
#2985
b1001001 &
1"
1$
#2990
0"
0$
#2995
b1001010 &
1"
1$
#3000
0"
0$
#3005
b1001011 &
1"
1$
