DivisorFrecuencia.v
module DivisorFrecuencia (
  input wire clk,
  input wire reset,
  output wire out
);
  reg clk_1M = 0;
  reg [31:0] cntr_1M = 32'b0;
  parameter period_1M = 25;
  always @ (posedge clk) begin
        /* generate 1M Hz clock */
        cntr_1M <= cntr_1M + 1;
        if (cntr_1M == period_1M) begin
            clk_1M <= ~clk_1M;
            cntr_1M <= 32'b0;
        end
  end

  assign out = clk_1M;

endmodule

DivisorFrecuencia_tb.v
`timescale 1ns/1ns

module DivisorFrecuencia_tb;

  reg clk;
  reg reset;
  wire out;

  DivisorFrecuencia uut (
    .clk(clk),
    .reset(reset),
    .out(out)
  );

  initial begin
    clk = 0;
    reset = 0;

    // Inicialización de la simulación
    $dumpfile("DivisorFrecuencia.vcd");
    $dumpvars(0, DivisorFrecuencia_tb);

    // Generación de pulsos de reloj
    repeat (200) begin
      #5 clk = ~clk;
    end

    // Aplicación de reset
    reset = 1;
    #10 reset = 0;

    // Ejecución de la simulación
    repeat (400) begin
      #5 clk = ~clk;
    end

    // Fin de la simulación
    $finish;
  end

endmodule

DivisorFrecuencia.vcd
$date
	Tue Dec 05 00:19:56 2023
$end
$version
	Icarus Verilog
$end
$timescale
	1ns
$end
$scope module DivisorFrecuencia_tb $end
$var wire 1 ! out $end
$var reg 1 " clk $end
$var reg 1 # reset $end
$scope module uut $end
$var wire 1 $ clk $end
$var wire 1 ! out $end
$var wire 1 % reset $end
$var reg 1 & clk_1M $end
$var reg 32 ' cntr_1M [31:0] $end
$upscope $end
$upscope $end
$enddefinitions $end
#0
$dumpvars
b0 '
0&
0%
0$
0#
0"
0!
$end
#5
b1 '
1"
1$
#10
0"
0$
#15
b10 '
1"
1$
#20
0"
0$
#25
b11 '
1"
1$
#30
0"
0$
#35
b100 '
1"
1$
#40
0"
0$
#45
b101 '
1"
1$
#50
0"
0$
#55
b110 '
1"
1$
#60
0"
0$
#65
b111 '
1"
1$
#70
0"
0$
#75
b1000 '
1"
1$
#80
0"
0$
#85
b1001 '
1"
1$
#90
0"
0$
#95
b1010 '
1"
1$
#100
0"
0$
#105
b1011 '
1"
1$
#110
0"
0$
#115
b1100 '
1"
1$
#120
0"
0$
#125
b1101 '
1"
1$
#130
0"
0$
#135
b1110 '
1"
1$
#140
0"
0$
#145
b1111 '
1"
1$
#150
0"
0$
#155
b10000 '
1"
1$
#160
0"
0$
#165
b10001 '
1"
1$
#170
0"
0$
#175
b10010 '
1"
1$
#180
0"
0$
#185
b10011 '
1"
1$
#190
0"
0$
#195
b10100 '
1"
1$
#200
0"
0$
#205
b10101 '
1"
1$
#210
0"
0$
#215
b10110 '
1"
1$
#220
0"
0$
#225
b10111 '
1"
1$
#230
0"
0$
#235
b11000 '
1"
1$
#240
0"
0$
#245
b11001 '
1"
1$
#250
0"
0$
#255
1&
1!
b0 '
1"
1$
#260
0"
0$
#265
b1 '
1"
1$
#270
0"
0$
#275
b10 '
1"
1$
#280
0"
0$
#285
b11 '
1"
1$
#290
0"
0$
#295
b100 '
1"
1$
#300
0"
0$
#305
b101 '
1"
1$
#310
0"
0$
#315
b110 '
1"
1$
#320
0"
0$
#325
b111 '
1"
1$
#330
0"
0$
#335
b1000 '
1"
1$
#340
0"
0$
#345
b1001 '
1"
1$
#350
0"
0$
#355
b1010 '
1"
1$
#360
0"
0$
#365
b1011 '
1"
1$
#370
0"
0$
#375
b1100 '
1"
1$
#380
0"
0$
#385
b1101 '
1"
1$
#390
0"
0$
#395
b1110 '
1"
1$
#400
0"
0$
#405
b1111 '
1"
1$
#410
0"
0$
#415
b10000 '
1"
1$
#420
0"
0$
#425
b10001 '
1"
1$
#430
0"
0$
#435
b10010 '
1"
1$
#440
0"
0$
#445
b10011 '
1"
1$
#450
0"
0$
#455
b10100 '
1"
1$
#460
0"
0$
#465
b10101 '
1"
1$
#470
0"
0$
#475
b10110 '
1"
1$
#480
0"
0$
#485
b10111 '
1"
1$
#490
0"
0$
#495
b11000 '
1"
1$
#500
0"
0$
#505
b11001 '
1"
1$
#510
0"
0$
#515
0&
0!
b0 '
1"
1$
#520
0"
0$
#525
b1 '
1"
1$
#530
0"
0$
#535
b10 '
1"
1$
#540
0"
0$
#545
b11 '
1"
1$
#550
0"
0$
#555
b100 '
1"
1$
#560
0"
0$
#565
b101 '
1"
1$
#570
0"
0$
#575
b110 '
1"
1$
#580
0"
0$
#585
b111 '
1"
1$
#590
0"
0$
#595
b1000 '
1"
1$
#600
0"
0$
#605
b1001 '
1"
1$
#610
0"
0$
#615
b1010 '
1"
1$
#620
0"
0$
#625
b1011 '
1"
1$
#630
0"
0$
#635
b1100 '
1"
1$
#640
0"
0$
#645
b1101 '
1"
1$
#650
0"
0$
#655
b1110 '
1"
1$
#660
0"
0$
#665
b1111 '
1"
1$
#670
0"
0$
#675
b10000 '
1"
1$
#680
0"
0$
#685
b10001 '
1"
1$
#690
0"
0$
#695
b10010 '
1"
1$
#700
0"
0$
#705
b10011 '
1"
1$
#710
0"
0$
#715
b10100 '
1"
1$
#720
0"
0$
#725
b10101 '
1"
1$
#730
0"
0$
#735
b10110 '
1"
1$
#740
0"
0$
#745
b10111 '
1"
1$
#750
0"
0$
#755
b11000 '
1"
1$
#760
0"
0$
#765
b11001 '
1"
1$
#770
0"
0$
#775
1&
1!
b0 '
1"
1$
#780
0"
0$
#785
b1 '
1"
1$
#790
0"
0$
#795
b10 '
1"
1$
#800
0"
0$
#805
b11 '
1"
1$
#810
0"
0$
#815
b100 '
1"
1$
#820
0"
0$
#825
b101 '
1"
1$
#830
0"
0$
#835
b110 '
1"
1$
#840
0"
0$
#845
b111 '
1"
1$
#850
0"
0$
#855
b1000 '
1"
1$
#860
0"
0$
#865
b1001 '
1"
1$
#870
0"
0$
#875
b1010 '
1"
1$
#880
0"
0$
#885
b1011 '
1"
1$
#890
0"
0$
#895
b1100 '
1"
1$
#900
0"
0$
#905
b1101 '
1"
1$
#910
0"
0$
#915
b1110 '
1"
1$
#920
0"
0$
#925
b1111 '
1"
1$
#930
0"
0$
#935
b10000 '
1"
1$
#940
0"
0$
#945
b10001 '
1"
1$
#950
0"
0$
#955
b10010 '
1"
1$
#960
0"
0$
#965
b10011 '
1"
1$
#970
0"
0$
#975
b10100 '
1"
1$
#980
0"
0$
#985
b10101 '
1"
1$
#990
0"
0$
#995
b10110 '
1"
1$
#1000
1#
1%
0"
0$
#1010
0#
0%
#1015
b10111 '
1"
1$
#1020
0"
0$
#1025
b11000 '
1"
1$
#1030
0"
0$
#1035
b11001 '
1"
1$
#1040
0"
0$
#1045
0&
0!
b0 '
1"
1$
#1050
0"
0$
#1055
b1 '
1"
1$
#1060
0"
0$
#1065
b10 '
1"
1$
#1070
0"
0$
#1075
b11 '
1"
1$
#1080
0"
0$
#1085
b100 '
1"
1$
#1090
0"
0$
#1095
b101 '
1"
1$
#1100
0"
0$
#1105
b110 '
1"
1$
#1110
0"
0$
#1115
b111 '
1"
1$
#1120
0"
0$
#1125
b1000 '
1"
1$
#1130
0"
0$
#1135
b1001 '
1"
1$
#1140
0"
0$
#1145
b1010 '
1"
1$
#1150
0"
0$
#1155
b1011 '
1"
1$
#1160
0"
0$
#1165
b1100 '
1"
1$
#1170
0"
0$
#1175
b1101 '
1"
1$
#1180
0"
0$
#1185
b1110 '
1"
1$
#1190
0"
0$
#1195
b1111 '
1"
1$
#1200
0"
0$
#1205
b10000 '
1"
1$
#1210
0"
0$
#1215
b10001 '
1"
1$
#1220
0"
0$
#1225
b10010 '
1"
1$
#1230
0"
0$
#1235
b10011 '
1"
1$
#1240
0"
0$
#1245
b10100 '
1"
1$
#1250
0"
0$
#1255
b10101 '
1"
1$
#1260
0"
0$
#1265
b10110 '
1"
1$
#1270
0"
0$
#1275
b10111 '
1"
1$
#1280
0"
0$
#1285
b11000 '
1"
1$
#1290
0"
0$
#1295
b11001 '
1"
1$
#1300
0"
0$
#1305
1&
1!
b0 '
1"
1$
#1310
0"
0$
#1315
b1 '
1"
1$
#1320
0"
0$
#1325
b10 '
1"
1$
#1330
0"
0$
#1335
b11 '
1"
1$
#1340
0"
0$
#1345
b100 '
1"
1$
#1350
0"
0$
#1355
b101 '
1"
1$
#1360
0"
0$
#1365
b110 '
1"
1$
#1370
0"
0$
#1375
b111 '
1"
1$
#1380
0"
0$
#1385
b1000 '
1"
1$
#1390
0"
0$
#1395
b1001 '
1"
1$
#1400
0"
0$
#1405
b1010 '
1"
1$
#1410
0"
0$
#1415
b1011 '
1"
1$
#1420
0"
0$
#1425
b1100 '
1"
1$
#1430
0"
0$
#1435
b1101 '
1"
1$
#1440
0"
0$
#1445
b1110 '
1"
1$
#1450
0"
0$
#1455
b1111 '
1"
1$
#1460
0"
0$
#1465
b10000 '
1"
1$
#1470
0"
0$
#1475
b10001 '
1"
1$
#1480
0"
0$
#1485
b10010 '
1"
1$
#1490
0"
0$
#1495
b10011 '
1"
1$
#1500
0"
0$
#1505
b10100 '
1"
1$
#1510
0"
0$
#1515
b10101 '
1"
1$
#1520
0"
0$
#1525
b10110 '
1"
1$
#1530
0"
0$
#1535
b10111 '
1"
1$
#1540
0"
0$
#1545
b11000 '
1"
1$
#1550
0"
0$
#1555
b11001 '
1"
1$
#1560
0"
0$
#1565
0&
0!
b0 '
1"
1$
#1570
0"
0$
#1575
b1 '
1"
1$
#1580
0"
0$
#1585
b10 '
1"
1$
#1590
0"
0$
#1595
b11 '
1"
1$
#1600
0"
0$
#1605
b100 '
1"
1$
#1610
0"
0$
#1615
b101 '
1"
1$
#1620
0"
0$
#1625
b110 '
1"
1$
#1630
0"
0$
#1635
b111 '
1"
1$
#1640
0"
0$
#1645
b1000 '
1"
1$
#1650
0"
0$
#1655
b1001 '
1"
1$
#1660
0"
0$
#1665
b1010 '
1"
1$
#1670
0"
0$
#1675
b1011 '
1"
1$
#1680
0"
0$
#1685
b1100 '
1"
1$
#1690
0"
0$
#1695
b1101 '
1"
1$
#1700
0"
0$
#1705
b1110 '
1"
1$
#1710
0"
0$
#1715
b1111 '
1"
1$
#1720
0"
0$
#1725
b10000 '
1"
1$
#1730
0"
0$
#1735
b10001 '
1"
1$
#1740
0"
0$
#1745
b10010 '
1"
1$
#1750
0"
0$
#1755
b10011 '
1"
1$
#1760
0"
0$
#1765
b10100 '
1"
1$
#1770
0"
0$
#1775
b10101 '
1"
1$
#1780
0"
0$
#1785
b10110 '
1"
1$
#1790
0"
0$
#1795
b10111 '
1"
1$
#1800
0"
0$
#1805
b11000 '
1"
1$
#1810
0"
0$
#1815
b11001 '
1"
1$
#1820
0"
0$
#1825
1&
1!
b0 '
1"
1$
#1830
0"
0$
#1835
b1 '
1"
1$
#1840
0"
0$
#1845
b10 '
1"
1$
#1850
0"
0$
#1855
b11 '
1"
1$
#1860
0"
0$
#1865
b100 '
1"
1$
#1870
0"
0$
#1875
b101 '
1"
1$
#1880
0"
0$
#1885
b110 '
1"
1$
#1890
0"
0$
#1895
b111 '
1"
1$
#1900
0"
0$
#1905
b1000 '
1"
1$
#1910
0"
0$
#1915
b1001 '
1"
1$
#1920
0"
0$
#1925
b1010 '
1"
1$
#1930
0"
0$
#1935
b1011 '
1"
1$
#1940
0"
0$
#1945
b1100 '
1"
1$
#1950
0"
0$
#1955
b1101 '
1"
1$
#1960
0"
0$
#1965
b1110 '
1"
1$
#1970
0"
0$
#1975
b1111 '
1"
1$
#1980
0"
0$
#1985
b10000 '
1"
1$
#1990
0"
0$
#1995
b10001 '
1"
1$
#2000
0"
0$
#2005
b10010 '
1"
1$
#2010
0"
0$
#2015
b10011 '
1"
1$
#2020
0"
0$
#2025
b10100 '
1"
1$
#2030
0"
0$
#2035
b10101 '
1"
1$
#2040
0"
0$
#2045
b10110 '
1"
1$
#2050
0"
0$
#2055
b10111 '
1"
1$
#2060
0"
0$
#2065
b11000 '
1"
1$
#2070
0"
0$
#2075
b11001 '
1"
1$
#2080
0"
0$
#2085
0&
0!
b0 '
1"
1$
#2090
0"
0$
#2095
b1 '
1"
1$
#2100
0"
0$
#2105
b10 '
1"
1$
#2110
0"
0$
#2115
b11 '
1"
1$
#2120
0"
0$
#2125
b100 '
1"
1$
#2130
0"
0$
#2135
b101 '
1"
1$
#2140
0"
0$
#2145
b110 '
1"
1$
#2150
0"
0$
#2155
b111 '
1"
1$
#2160
0"
0$
#2165
b1000 '
1"
1$
#2170
0"
0$
#2175
b1001 '
1"
1$
#2180
0"
0$
#2185
b1010 '
1"
1$
#2190
0"
0$
#2195
b1011 '
1"
1$
#2200
0"
0$
#2205
b1100 '
1"
1$
#2210
0"
0$
#2215
b1101 '
1"
1$
#2220
0"
0$
#2225
b1110 '
1"
1$
#2230
0"
0$
#2235
b1111 '
1"
1$
#2240
0"
0$
#2245
b10000 '
1"
1$
#2250
0"
0$
#2255
b10001 '
1"
1$
#2260
0"
0$
#2265
b10010 '
1"
1$
#2270
0"
0$
#2275
b10011 '
1"
1$
#2280
0"
0$
#2285
b10100 '
1"
1$
#2290
0"
0$
#2295
b10101 '
1"
1$
#2300
0"
0$
#2305
b10110 '
1"
1$
#2310
0"
0$
#2315
b10111 '
1"
1$
#2320
0"
0$
#2325
b11000 '
1"
1$
#2330
0"
0$
#2335
b11001 '
1"
1$
#2340
0"
0$
#2345
1&
1!
b0 '
1"
1$
#2350
0"
0$
#2355
b1 '
1"
1$
#2360
0"
0$
#2365
b10 '
1"
1$
#2370
0"
0$
#2375
b11 '
1"
1$
#2380
0"
0$
#2385
b100 '
1"
1$
#2390
0"
0$
#2395
b101 '
1"
1$
#2400
0"
0$
#2405
b110 '
1"
1$
#2410
0"
0$
#2415
b111 '
1"
1$
#2420
0"
0$
#2425
b1000 '
1"
1$
#2430
0"
0$
#2435
b1001 '
1"
1$
#2440
0"
0$
#2445
b1010 '
1"
1$
#2450
0"
0$
#2455
b1011 '
1"
1$
#2460
0"
0$
#2465
b1100 '
1"
1$
#2470
0"
0$
#2475
b1101 '
1"
1$
#2480
0"
0$
#2485
b1110 '
1"
1$
#2490
0"
0$
#2495
b1111 '
1"
1$
#2500
0"
0$
#2505
b10000 '
1"
1$
#2510
0"
0$
#2515
b10001 '
1"
1$
#2520
0"
0$
#2525
b10010 '
1"
1$
#2530
0"
0$
#2535
b10011 '
1"
1$
#2540
0"
0$
#2545
b10100 '
1"
1$
#2550
0"
0$
#2555
b10101 '
1"
1$
#2560
0"
0$
#2565
b10110 '
1"
1$
#2570
0"
0$
#2575
b10111 '
1"
1$
#2580
0"
0$
#2585
b11000 '
1"
1$
#2590
0"
0$
#2595
b11001 '
1"
1$
#2600
0"
0$
#2605
0&
0!
b0 '
1"
1$
#2610
0"
0$
#2615
b1 '
1"
1$
#2620
0"
0$
#2625
b10 '
1"
1$
#2630
0"
0$
#2635
b11 '
1"
1$
#2640
0"
0$
#2645
b100 '
1"
1$
#2650
0"
0$
#2655
b101 '
1"
1$
#2660
0"
0$
#2665
b110 '
1"
1$
#2670
0"
0$
#2675
b111 '
1"
1$
#2680
0"
0$
#2685
b1000 '
1"
1$
#2690
0"
0$
#2695
b1001 '
1"
1$
#2700
0"
0$
#2705
b1010 '
1"
1$
#2710
0"
0$
#2715
b1011 '
1"
1$
#2720
0"
0$
#2725
b1100 '
1"
1$
#2730
0"
0$
#2735
b1101 '
1"
1$
#2740
0"
0$
#2745
b1110 '
1"
1$
#2750
0"
0$
#2755
b1111 '
1"
1$
#2760
0"
0$
#2765
b10000 '
1"
1$
#2770
0"
0$
#2775
b10001 '
1"
1$
#2780
0"
0$
#2785
b10010 '
1"
1$
#2790
0"
0$
#2795
b10011 '
1"
1$
#2800
0"
0$
#2805
b10100 '
1"
1$
#2810
0"
0$
#2815
b10101 '
1"
1$
#2820
0"
0$
#2825
b10110 '
1"
1$
#2830
0"
0$
#2835
b10111 '
1"
1$
#2840
0"
0$
#2845
b11000 '
1"
1$
#2850
0"
0$
#2855
b11001 '
1"
1$
#2860
0"
0$
#2865
1&
1!
b0 '
1"
1$
#2870
0"
0$
#2875
b1 '
1"
1$
#2880
0"
0$
#2885
b10 '
1"
1$
#2890
0"
0$
#2895
b11 '
1"
1$
#2900
0"
0$
#2905
b100 '
1"
1$
#2910
0"
0$
#2915
b101 '
1"
1$
#2920
0"
0$
#2925
b110 '
1"
1$
#2930
0"
0$
#2935
b111 '
1"
1$
#2940
0"
0$
#2945
b1000 '
1"
1$
#2950
0"
0$
#2955
b1001 '
1"
1$
#2960
0"
0$
#2965
b1010 '
1"
1$
#2970
0"
0$
#2975
b1011 '
1"
1$
#2980
0"
0$
#2985
b1100 '
1"
1$
#2990
0"
0$
#2995
b1101 '
1"
1$
#3000
0"
0$
#3005
b1110 '
1"
1$
