DelayModule.v
module DelayModule (
  input wire clk,          // Señal de reloj
  input wire rst,          // Señal de reinicio
  input wire [8:0] delay,   // Valor de delay de 9 bits
  output reg out_delay     // Salida de delay
);

  reg [8:0] count;          // Contador de delay

  always @(posedge clk or posedge rst) begin
    if (rst) begin
      count <= 0;           // Reiniciar contador en caso de reinicio
      out_delay <= 0;       // Reiniciar salida en caso de reinicio
    end else begin
      if (count == delay) begin
        out_delay <= 1;     // Activar salida después del delay
        count <= 0;         // Reiniciar contador después del delay
      end else begin
        count <= count + 1; // Incrementar contador si no se alcanza el delay
        out_delay <= 0;     // Desactivar salida durante el delay
      end
    end
  end

endmodule

ReadModule.v
module ReadModule (
  input wire clk,          // Señal de reloj
  input wire rst,          // Señal de reinicio
  input wire in_data,      // Entrada de datos
  output reg out_data      // Salida de datos
);

  reg [0:0] D1, D2, D;      // Variables para almacenar datos
  wire out_delay;          // Señal de salida del DelayModule
  reg [8:0] delay1 = 10;    // Delay de 10 ciclos para 1 microsegundo
  reg [8:0] delay2 = 600;   // Delay de 600 ciclos para 60 microsegundos

  // Instancia del DelayModule
  DelayModule delay_module (
    .clk(clk),
    .rst(rst),
    .delay(delay1),
    .out_delay(out_delay)
  );

  // Proceso principal
  always @(posedge clk or posedge rst) begin
    if (rst) begin
      // Reiniciar variables en caso de reinicio
      D1 <= 0;
      D2 <= 0;
      D <= 0;
      out_data <= 0;
    end else begin
      // Activar salida durante el primer delay
      if (out_delay) begin
        // Guardar el bit de entrada en D1
        D1 <= in_data;
      end

      // Activar salida durante el segundo delay
      if (out_delay) begin
        // Guardar el bit de entrada en D2
        D2 <= in_data;
      end

      // Comparar D1 y D2
      if (D1 == D2) begin
        // Si son iguales, guardar D1 en D
        D <= D1;
        out_data <= D;
      end else begin
        // Si son diferentes, imprimir "ERROR"
        $display("ERROR");
      end
    end
  end

endmodule

ReadModule_tb.v
`timescale 1us/1us  // Definición de la escala de tiempo

module ReadModule_tb;

  reg clk;
  reg rst;
  reg in_data;
  wire out_data;

  // Instancia del módulo bajo prueba
  ReadModule uut (
    .clk(clk),
    .rst(rst),
    .in_data(in_data),
    .out_data(out_data)
  );

  // Generación de un pulso de reloj
  always #5 clk = ~clk;

  // Inicialización de señales
  initial begin
    clk = 0;
    rst = 1;
    in_data = 0;

    // Esperar un poco antes de desactivar el reset
    #10 rst = 0;

    // Simular durante 1000 unidades de tiempo
    #1000 $finish;
  end

    // Dumpfile y Dumpvars
    initial begin
     	$dumpfile("ReadModule.vcd");
    	$dumpvars(0, ReadModule_tb);
     end



endmodule

ReadModule.vcd
$date
	Sun Nov 19 19:44:20 2023
$end
$version
	Icarus Verilog
$end
$timescale
	1us
$end
$scope module ReadModule_tb $end
$var wire 1 ! out_data $end
$var reg 1 " clk $end
$var reg 1 # in_data $end
$var reg 1 $ rst $end
$scope module uut $end
$var wire 1 % clk $end
$var wire 1 & in_data $end
$var wire 1 ' out_delay $end
$var wire 1 ( rst $end
$var reg 1 ) D $end
$var reg 1 * D1 $end
$var reg 1 + D2 $end
$var reg 9 , delay1 [8:0] $end
$var reg 9 - delay2 [8:0] $end
$var reg 1 . out_data $end
$scope module delay_module $end
$var wire 1 % clk $end
$var wire 9 / delay [8:0] $end
$var wire 1 ( rst $end
$var reg 9 0 count [8:0] $end
$var reg 1 1 out_delay $end
$upscope $end
$upscope $end
$upscope $end
$enddefinitions $end
#0
$dumpvars
01
b0 0
b1010 /
0.
b1011000 -
b1010 ,
0+
0*
0)
1(
0'
0&
0%
1$
0#
0"
0!
$end
#5
1"
1%
#10
0"
0%
0$
0(
#15
b1 0
1"
1%
#20
0"
0%
#25
b10 0
1"
1%
#30
0"
0%
#35
b11 0
1"
1%
#40
0"
0%
#45
b100 0
1"
1%
#50
0"
0%
#55
b101 0
1"
1%
#60
0"
0%
#65
b110 0
1"
1%
#70
0"
0%
#75
b111 0
1"
1%
#80
0"
0%
#85
b1000 0
1"
1%
#90
0"
0%
#95
b1001 0
1"
1%
#100
0"
0%
#105
b1010 0
1"
1%
#110
0"
0%
#115
b0 0
11
1'
1"
1%
#120
0"
0%
#125
01
0'
b1 0
1"
1%
#130
0"
0%
#135
b10 0
1"
1%
#140
0"
0%
#145
b11 0
1"
1%
#150
0"
0%
#155
b100 0
1"
1%
#160
0"
0%
#165
b101 0
1"
1%
#170
0"
0%
#175
b110 0
1"
1%
#180
0"
0%
#185
b111 0
1"
1%
#190
0"
0%
#195
b1000 0
1"
1%
#200
0"
0%
#205
b1001 0
1"
1%
#210
0"
0%
#215
b1010 0
1"
1%
#220
0"
0%
#225
b0 0
11
1'
1"
1%
#230
0"
0%
#235
01
0'
b1 0
1"
1%
#240
0"
0%
#245
b10 0
1"
1%
#250
0"
0%
#255
b11 0
1"
1%
#260
0"
0%
#265
b100 0
1"
1%
#270
0"
0%
#275
b101 0
1"
1%
#280
0"
0%
#285
b110 0
1"
1%
#290
0"
0%
#295
b111 0
1"
1%
#300
0"
0%
#305
b1000 0
1"
1%
#310
0"
0%
#315
b1001 0
1"
1%
#320
0"
0%
#325
b1010 0
1"
1%
#330
0"
0%
#335
b0 0
11
1'
1"
1%
#340
0"
0%
#345
01
0'
b1 0
1"
1%
#350
0"
0%
#355
b10 0
1"
1%
#360
0"
0%
#365
b11 0
1"
1%
#370
0"
0%
#375
b100 0
1"
1%
#380
0"
0%
#385
b101 0
1"
1%
#390
0"
0%
#395
b110 0
1"
1%
#400
0"
0%
#405
b111 0
1"
1%
#410
0"
0%
#415
b1000 0
1"
1%
#420
0"
0%
#425
b1001 0
1"
1%
#430
0"
0%
#435
b1010 0
1"
1%
#440
0"
0%
#445
b0 0
11
1'
1"
1%
#450
0"
0%
#455
01
0'
b1 0
1"
1%
#460
0"
0%
#465
b10 0
1"
1%
#470
0"
0%
#475
b11 0
1"
1%
#480
0"
0%
#485
b100 0
1"
1%
#490
0"
0%
#495
b101 0
1"
1%
#500
0"
0%
#505
b110 0
1"
1%
#510
0"
0%
#515
b111 0
1"
1%
#520
0"
0%
#525
b1000 0
1"
1%
#530
0"
0%
#535
b1001 0
1"
1%
#540
0"
0%
#545
b1010 0
1"
1%
#550
0"
0%
#555
b0 0
11
1'
1"
1%
#560
0"
0%
#565
01
0'
b1 0
1"
1%
#570
0"
0%
#575
b10 0
1"
1%
#580
0"
0%
#585
b11 0
1"
1%
#590
0"
0%
#595
b100 0
1"
1%
#600
0"
0%
#605
b101 0
1"
1%
#610
0"
0%
#615
b110 0
1"
1%
#620
0"
0%
#625
b111 0
1"
1%
#630
0"
0%
#635
b1000 0
1"
1%
#640
0"
0%
#645
b1001 0
1"
1%
#650
0"
0%
#655
b1010 0
1"
1%
#660
0"
0%
#665
b0 0
11
1'
1"
1%
#670
0"
0%
#675
01
0'
b1 0
1"
1%
#680
0"
0%
#685
b10 0
1"
1%
#690
0"
0%
#695
b11 0
1"
1%
#700
0"
0%
#705
b100 0
1"
1%
#710
0"
0%
#715
b101 0
1"
1%
#720
0"
0%
#725
b110 0
1"
1%
#730
0"
0%
#735
b111 0
1"
1%
#740
0"
0%
#745
b1000 0
1"
1%
#750
0"
0%
#755
b1001 0
1"
1%
#760
0"
0%
#765
b1010 0
1"
1%
#770
0"
0%
#775
b0 0
11
1'
1"
1%
#780
0"
0%
#785
01
0'
b1 0
1"
1%
#790
0"
0%
#795
b10 0
1"
1%
#800
0"
0%
#805
b11 0
1"
1%
#810
0"
0%
#815
b100 0
1"
1%
#820
0"
0%
#825
b101 0
1"
1%
#830
0"
0%
#835
b110 0
1"
1%
#840
0"
0%
#845
b111 0
1"
1%
#850
0"
0%
#855
b1000 0
1"
1%
#860
0"
0%
#865
b1001 0
1"
1%
#870
0"
0%
#875
b1010 0
1"
1%
#880
0"
0%
#885
b0 0
11
1'
1"
1%
#890
0"
0%
#895
01
0'
b1 0
1"
1%
#900
0"
0%
#905
b10 0
1"
1%
#910
0"
0%
#915
b11 0
1"
1%
#920
0"
0%
#925
b100 0
1"
1%
#930
0"
0%
#935
b101 0
1"
1%
#940
0"
0%
#945
b110 0
1"
1%
#950
0"
0%
#955
b111 0
1"
1%
#960
0"
0%
#965
b1000 0
1"
1%
#970
0"
0%
#975
b1001 0
1"
1%
#980
0"
0%
#985
b1010 0
1"
1%
#990
0"
0%
#995
b0 0
11
1'
1"
1%
#1000
0"
0%
#1005
01
0'
b1 0
1"
1%
